[{"subject": "ECOLOGY, EVOLUTION AND NATURAL RESOURCES 216"}, [{"className": "PRACT EXP IN EENR 440", "coreStuff": []}, {"className": "RES PROB ECL EVO N R 484", "coreStuff": []}, {"className": "INTRO TO ECOL & EVOL 101", "coreStuff": [{"coreDescription": "Natural Sciences", "code": "NS"}]}, {"className": "FUNDAMENTALS OF EVOLUTION 251", "coreStuff": []}, {"className": "FUNDAMENTALS OF EVOLUTION LABORATORY 252", "coreStuff": []}, {"className": "FIELD TECHNIQUES 274", "coreStuff": []}, {"className": "CONSERVATION ECOLOGY 317", "coreStuff": [{"coreDescription": "21st Century Challenges", "code": "21C"}, {"coreDescription": "Writing and Communication in a Discipline", "code": "WCd"}]}, {"className": "ORNITHOLOGY 323", "coreStuff": []}, {"className": "VERTEBRATE ZOOLOGY 325", "coreStuff": []}, {"className": "LIMNOLOGY 335", "coreStuff": []}, {"className": "PRINCIPLES OF ECOL 351", "coreStuff": []}, {"className": "PRINCIPLES OF ECOLOGY LABORATORY 352", "coreStuff": []}, {"className": "ANAL MTDS ECL EVL NR 369", "coreStuff": []}, {"className": "PRACTICUM IN FOREST MANAGEMENT 377", "coreStuff": []}, {"className": "URBAN FORESTRY 403", "coreStuff": []}, {"className": "SPECIAL TOPICS IN ECOLOGY, EVOLUTION,ANDNATURAL RESOURCES 407", "coreStuff": []}, {"className": "ENVIRONMENTAL EDUCATION 416", "coreStuff": []}, {"className": "FUNDAMENTALS OF GENOMICS 423", "coreStuff": []}, {"className": "CONVERS BIO-MATH 428", "coreStuff": []}, {"className": "ANIMAL BEHAVIOR 441", "coreStuff": []}, {"className": "CHINA ECOL AGR IMPCT 468", "coreStuff": []}, {"className": "WILDLIFE DISEASES 469", "coreStuff": []}, {"className": "ADV REMOTE SENSING 474", "coreStuff": []}, {"className": "PRINC OF EVOLUTION 486", "coreStuff": []}, {"className": "URBAN ECOLOGY 487", "coreStuff": []}, {"className": "SENIOR CAPSTONE - ECOLOGY, EVOLUTION & NATURAL RESOURCES 499", "coreStuff": []}, {"className": "SUSTAINABLE ENVIRONMENTAL MANAGEMENT 320", "coreStuff": []}, {"className": "CONSERVATION TECHNIQUES 470", "coreStuff": []}, {"className": "TPC ECO EVOL NAT RES 104", "coreStuff": []}, {"className": "EVOL DISEASE & MED 110", "coreStuff": [{"coreDescription": "Natural Sciences", "code": "NS"}]}, {"className": "EVOLUTION OF SEX AND GENDER IN ANIMALS 115", "coreStuff": [{"coreDescription": "21st Century Challenges", "code": "21C"}, {"coreDescription": "Natural Sciences", "code": "NS"}]}, {"className": "THE NATURAL RESOURCE PROFESSIONS 211", "coreStuff": []}, {"className": "PRINCIPLES OF NATURAL RESOURCE MANAGEMENT 217", "coreStuff": []}, {"className": "BEHAVIORAL BIOLOGY 240", "coreStuff": []}, {"className": "EVOLUTION OF ANIMAL BEHAVIOR 269", "coreStuff": []}, {"className": "DENDROLOGY 272", "coreStuff": []}, {"className": "HONORS SEMINAR IN ECOLOGY, EVOLUTION AND NATURAL RESOURCES 296", "coreStuff": []}, {"className": "PARASITE ECOLOGY 302", "coreStuff": []}, {"className": "SPECIAL TOPICS IN ECOLOGY, EVOLUTION,ANDNATURAL RESOURCES 306", "coreStuff": []}, {"className": "INVERTEBRATE ZOOLOGY 324", "coreStuff": []}, {"className": "PLANT ECOLOGY 332", "coreStuff": []}, {"className": "ANIMAL PHYSIOLOGICAL ECOLOGY 360", "coreStuff": []}, {"className": "ARBORICULTURE 365", "coreStuff": []}, {"className": "INTRODUCTORY REMOTE SENSING IMAGE ANALYS 371", "coreStuff": []}, {"className": "THE EVOLUTION OF EUKARYOTES 401", "coreStuff": []}, {"className": "SPECIAL TOPICS IN ECOLOGY, EVOLUTION, & NATURAL RESOURCES 406", "coreStuff": []}, {"className": "PLANT DIVERSITY AND EVOLUTION 411", "coreStuff": []}, {"className": "PLANT DIVERSITY AND EVOLUTION LABORATORY 412", "coreStuff": []}, {"className": "LANDSCAPE ECOLOGY 450", "coreStuff": []}, {"className": "GLOBAL CHANGE AND ECOLOGY 451", "coreStuff": []}, {"className": "WILDLIFE ECOLOGY AND CONSERVATION 464", "coreStuff": []}, {"className": "WINTER FIELD ECOLOGY 475", "coreStuff": []}, {"className": "INTRODUCTION TO ECOLOGY AND EVOLUTION 101", "coreStuff": [{"coreDescription": "Natural Sciences", "code": "NS"}]}, {"className": "PRINCIPLES OF ECOLOGY 351", "coreStuff": []}, {"className": "ANALYTICAL METHODS IN ECOLOGY, EVOLUTION& NATURAL RESOURCES 369", "coreStuff": []}, {"className": "PRACTICUM IN FISHERIES MANAGEMENT 376", "coreStuff": []}, {"className": "EVOLUTION OF INFECTIOUS DISEASES 405", "coreStuff": []}, {"className": "SOIL ORGANISMAL DIVERSITY 422", "coreStuff": []}, {"className": "FUNDAMENTALS OF ECOLOGICAL AND ENVIRONMENTAL MODELING 431", "coreStuff": []}, {"className": "MOLECULAR ECOLOGY 454", "coreStuff": []}, {"className": "SILVICULTURE 471", "coreStuff": []}, {"className": "PRINCIPLES OF EVOLUTION 486", "coreStuff": []}, {"className": "CONSERVATION TECHNIQUES 315", "coreStuff": []}, {"className": "EXPERIMENTAL EVOLUTION 353", "coreStuff": []}, {"className": "WETLAND ECOLOGY 421", "coreStuff": []}, {"className": "TREES & THE ENVIRON 456", "coreStuff": []}]]