[{"subject": "ENVIRONMENTAL AND BUSINESS ECONOMICS 373"}, [{"className": "CORPORATE CITIZENSHIP AND SOCIAL RESPONSIBILITY 201", "coreStuff": [{"coreDescription": "Social Analysis", "code": "SCL"}]}, {"className": "SUSTAINABLE FOOD POLICY FOR DEVELOPING COUNTRIES 218", "coreStuff": []}, {"className": "INTRO TO MARKETING 231", "coreStuff": []}, {"className": "NATURAL RESOURCE ECONOMICS 362", "coreStuff": [{"coreDescription": "Social Analysis", "code": "SCL"}]}, {"className": "RESEARCH PROBLEMS IN AGRICULTURAL, ENVIRONMENTAL, & BUSINESS ECONOMICS 491", "coreStuff": []}, {"className": "ECO PEOPLE AND ENV 101", "coreStuff": [{"coreDescription": "21st Century Challenges", "code": "21C"}, {"coreDescription": "Social Analysis", "code": "SCL"}]}, {"className": "PRIN&APP MICROECONM 121", "coreStuff": [{"coreDescription": "Social Analysis", "code": "SCL"}]}, {"className": "PRIN&APP MACROECONM 122", "coreStuff": [{"coreDescription": "Social Analysis", "code": "SCL"}]}, {"className": "SUSTAINABILITY DECISION TOOLS 202", "coreStuff": []}, {"className": "SMALL BUSINESS ESSEN 205", "coreStuff": []}, {"className": "BUS DECISION TOOLS I 210", "coreStuff": []}, {"className": "INTRO TO MANAGEMENT 241", "coreStuff": []}, {"className": "PUB POLICY FOOD IND 323", "coreStuff": []}, {"className": "ECON FOOD MKTG SYSTM 331", "coreStuff": []}, {"className": "ENERGY ECONOMICS AND POLICY 335", "coreStuff": []}, {"className": "MGT:HUMAN SYSTEM DEV 341", "coreStuff": []}, {"className": "ENVIRONMENTAL ECONOMICS 363", "coreStuff": []}, {"className": "GLOBAL MARKETING 402", "coreStuff": []}, {"className": "DEMAND AND PRICE ANALYSIS 422", "coreStuff": []}, {"className": "BUSINESS FINANCE II 451", "coreStuff": []}, {"className": "BUSINESS RESEARCH 465", "coreStuff": []}, {"className": "ISSUES IN AGRICULTURAL, ENVIRONMENTAL & BUSINESS ECONOMICS 495", "coreStuff": []}, {"className": "PRINCIPLES AND APPLICATIONS OF MICROECONOMICS 121", "coreStuff": [{"coreDescription": "Social Analysis", "code": "SCL"}]}, {"className": "FOOD HEALTH AND SAFETY POLICY 371", "coreStuff": []}, {"className": "INTERNATIONAL TRADE POLICY 431", "coreStuff": [{"coreDescription": "21st Century Challenges", "code": "21C"}]}, {"className": "APP MATH CON AG EC I 211", "coreStuff": []}, {"className": "APPL STAT BUS ECON 215", "coreStuff": []}, {"className": "ECON OF PRODUCTION 321", "coreStuff": []}, {"className": "BUSINESS FINANCE I 351", "coreStuff": []}, {"className": "ECON FUTURES MARKETS 352", "coreStuff": []}, {"className": "PERSONAL FINANCE 353", "coreStuff": []}, {"className": "LAND ECONOMICS 361", "coreStuff": []}, {"className": "INNOVATION/ENTREPREN 403", "coreStuff": []}, {"className": "ECONOMETRIC APPS 425", "coreStuff": []}, {"className": "RES PROB ENV&BUS ECO 492", "coreStuff": []}, {"className": "BIOSCIENCE POLICY 404", "coreStuff": []}, {"className": "ECONOMICS OF PRODUCTION 321", "coreStuff": []}, {"className": "RESEARCH PROBLEMS IN AGRICULTURAL, ENVIRONMENTAL, AND BUSINESS ECONOMICS 492", "coreStuff": []}]]