[{"subject": "SOCIOLOGY 920"}, [{"className": "SOCIOLOGICAL ANALYSIS OF SOCIAL PROBLEMS 103", "coreStuff": [{"coreDescription": "21st Century Challenges", "code": "21C"}, {"coreDescription": "Social Analysis", "code": "SCL"}]}, {"className": "INTRO TO SOCIOLOGY 101", "coreStuff": [{"coreDescription": "21st Century Challenges", "code": "21C"}, {"coreDescription": "Social Analysis", "code": "SCL"}]}, {"className": "SOC OF MED&HLTH CARE 210", "coreStuff": [{"coreDescription": "Social Analysis", "code": "SCL"}]}, {"className": "SOCIOLOGY OF WOMEN 216", "coreStuff": []}, {"className": "SOCIOLOGY OF EDUCATN 218", "coreStuff": []}, {"className": "CRIMINOLOGY 222", "coreStuff": [{"coreDescription": "Social Analysis", "code": "SCL"}]}, {"className": "HEALTH, CULTURE AND SOCIETY 226", "coreStuff": []}, {"className": "POPULATION & SOCIETY 227", "coreStuff": []}, {"className": "NORMALITY AND ABNORMALITY 240", "coreStuff": [{"coreDescription": "21st Century Challenges", "code": "21C"}, {"coreDescription": "Social Analysis", "code": "SCL"}, {"coreDescription": "Writing and Communication in a Discipline", "code": "WCd"}]}, {"className": "SOCIOLOGY OF SPORT 248", "coreStuff": []}, {"className": "SOCIOLOGY OF THE FAMILY 272", "coreStuff": []}, {"className": "SOC OF DEVIANT BEHAV 304", "coreStuff": []}, {"className": "RACE RELATIONS 306", "coreStuff": []}, {"className": "SOC MENTAL ILLNESS 307", "coreStuff": []}, {"className": "PSYCHOSOCIAL FOUNDATIONS OF HEALTH AND MEDICINE 308", "coreStuff": []}, {"className": "INTRO SOC RESEARCH 311", "coreStuff": [{"coreDescription": "Quantitative Information", "code": "QQ"}]}, {"className": "INTRODUCTION TO STATISTICS IN SOCIOLOGY 312", "coreStuff": [{"coreDescription": "Information Technology and Research", "code": "ITR"}, {"coreDescription": "Quantitative Information", "code": "QQ"}, {"coreDescription": "Mathematical or Formal Reasoning", "code": "QR"}]}, {"className": "DEV OF SOC THEORY 313", "coreStuff": []}, {"className": "CONTEMP SOCIOL THRY 314", "coreStuff": []}, {"className": "HOW ORGANIZATIONS WORK 315", "coreStuff": []}, {"className": "SOC APRRCH SOC PSYCH 319", "coreStuff": []}, {"className": "HEALTH & INEQUALITY 335", "coreStuff": []}, {"className": "LAW AND SOCIETY 349", "coreStuff": []}, {"className": "SOC OF DRUG USE 361", "coreStuff": []}, {"className": "GLOBAL STRUCTURES AND CHANGE 370", "coreStuff": []}, {"className": "RESEARCH IN SOCIOLOGY 395", "coreStuff": []}, {"className": "CESEP 399", "coreStuff": []}, {"className": "SEMINAR IN SOCIOLOGY 422", "coreStuff": []}, {"className": "SEXUALITY & SOCIETY 440", "coreStuff": []}, {"className": "SEM SOC OF GENDER 470", "coreStuff": []}, {"className": "ADV SEM IN SOC 492", "coreStuff": []}, {"className": "INDEP STUDY IN SOC 493", "coreStuff": []}, {"className": "RESEARCH IN SOCIOL 496", "coreStuff": []}, {"className": "HONORS IN SOCIOLOGY 498", "coreStuff": []}, {"className": "MINORITY GROUPS IN AMERICAN SOCIETY 108", "coreStuff": [{"coreDescription": "21st Century Challenges", "code": "21C"}, {"coreDescription": "Social Analysis", "code": "SCL"}]}, {"className": "MASS COMMUNICATION IN MODERN SOCIETY 205", "coreStuff": [{"coreDescription": "Social Analysis", "code": "SCL"}]}, {"className": "SOCIOLOGY OF DEVIANT BEHAVIOR 304", "coreStuff": []}, {"className": "SOCIOLOGY OF MENTAL ILLNESS 307", "coreStuff": []}, {"className": "INTRODUCTION TO SOCIAL RESEARCH 311", "coreStuff": [{"coreDescription": "Quantitative Information", "code": "QQ"}]}, {"className": "DEVELOPMENT OF SOCIOLOGICAL THEORY 313", "coreStuff": []}, {"className": "CONTEMPORARY SOCIOLOGICAL THEORIES 314", "coreStuff": []}, {"className": "SOCIOLOGY OF GENDER 324", "coreStuff": []}, {"className": "INDEPENDENT STUDY IN SOCIOLOGY 493", "coreStuff": []}, {"className": "RESEARCH IN SOCIOLOGY 495", "coreStuff": []}, {"className": "SOCIOLOGY OF FOOD AND EATING 232", "coreStuff": []}, {"className": "GLOBAL INEQUALITIES 270", "coreStuff": []}, {"className": "SOCIAL GERONTOLOGY 303", "coreStuff": []}, {"className": "SOCIAL INEQUALITIES 332", "coreStuff": []}, {"className": "SOCIOLOGY OF SEXUALITY 340", "coreStuff": []}, {"className": "FIELD STUDY IN SOCIO 385", "coreStuff": []}, {"className": "SEMINAR IN SOCIOLOGY 421", "coreStuff": []}, {"className": "SOC OF CITIES&SUBURB 428", "coreStuff": []}, {"className": "ADV SEM IN SOC 491", "coreStuff": []}, {"className": "RESEARCH IN SOCIOL 495", "coreStuff": []}, {"className": "HONORS IN SOCIOLOGY 497", "coreStuff": []}, {"className": "INDIVIDUAL & SOCIETY 283", "coreStuff": []}, {"className": "ENVIRON SOCIOLOGY 359", "coreStuff": []}, {"className": "IMMGRNT MINORTIES US 435", "coreStuff": []}, {"className": "SOCIOLOGY OF CULTURE 220", "coreStuff": []}, {"className": "POLITICAL SOCIOLOGY 290", "coreStuff": []}]]